microcotb/__init__.py
microcotb/clock.py
microcotb/dut.py
microcotb/log.py
microcotb/runner.py
microcotb/sub_signals.py
microcotb/testcase.py
microcotb/decorators/__init__.py
microcotb/decorators/decorators.py
microcotb/decorators/parametrize_default.py
microcotb/decorators/parametrize_simple.py
microcotb/decorators/parametrized.py
microcotb/monitorable/__init__.py
microcotb/monitorable/dut.py
microcotb/monitorable/io.py
microcotb/monitorable/state_tracking.py
microcotb/monitorable/vcd_writer.py
microcotb/platform/__init__.py
microcotb/platform/detection.py
microcotb/platform/features.py
microcotb/platform/dummy/__init__.py
microcotb/platform/dummy/pin.py
microcotb/platform/dummy/time.py
microcotb/platform/rp2040/__init__.py
microcotb/platform/rp2040/pin.py
microcotb/ports/__init__.py
microcotb/ports/io.py
microcotb/time/__init__.py
microcotb/time/system.py
microcotb/time/value.py
microcotb/triggers/__init__.py
microcotb/triggers/awaitable.py
microcotb/triggers/clockcycles.py
microcotb/triggers/edge.py
microcotb/triggers/timer.py
microcotb/types/__init__.py
microcotb/types/array.py
microcotb/types/handle.py
microcotb/types/ioport.py
microcotb/types/logic.py
microcotb/types/logic_array.py
microcotb/types/range.py
microcotb/types/with_value.py
microcotb/utils/__init__.py
microcotb/utils/tm.py
microcotb_rpi/__init__.py
microcotb_rpi/dut.py
microcotb_rpi/io.py
microcotb_rpi/simple_io.py
microcotb_sub/__init__.py
microcotb_sub/dut.py
microcotb_sub/dut_sub.py
microcotb_sub/io.py
microcotb_sub/signal.py
microcotb-0.7.6.dist-info/LICENSE
microcotb-0.7.6.dist-info/METADATA
microcotb-0.7.6.dist-info/WHEEL
microcotb-0.7.6.dist-info/top_level.txt
microcotb-0.7.6.dist-info/RECORD
