Metadata-Version: 2.1
Name: microcotb
Version: 0.7.6
Summary: A cocotb implementation for hardware in the loop and uPython 
Author: Pat Deegan
Project-URL: Homepage, https://microcotb.org
Project-URL: Issues, https://github.com/psychogenic/microcotb/issues
Classifier: Programming Language :: Python :: 3
Classifier: License :: OSI Approved :: GNU Lesser General Public License v2 or later (LGPLv2+)
Classifier: Operating System :: OS Independent
Requires-Python: >=3.8
License-File: LICENSE
Requires-Dist: pyvcd
